[
    {
        "datetime": "2025-04-04T00:00",
        "daylight": "night",
        "lowtide": "",
        "wind_direction": 60,
        "wind_speed": 2.7,
        "wind_gusts": 8.0
    },
    {
        "datetime": "2025-04-04T01:00",
        "daylight": "night",
        "lowtide": "",
        "wind_direction": 13,
        "wind_speed": 2.6,
        "wind_gusts": 5.1
    },
    {
        "datetime": "2025-04-04T02:00",
        "daylight": "night",
        "lowtide": "",
        "wind_direction": 351,
        "wind_speed": 2.6,
        "wind_gusts": 4.5
    },
    {
        "datetime": "2025-04-04T03:00",
        "daylight": "night",
        "lowtide": "",
        "wind_direction": 8,
        "wind_speed": 4.1,
        "wind_gusts": 6.4
    },
    {
        "datetime": "2025-04-04T04:00",
        "daylight": "night",
        "lowtide": "",
        "wind_direction": 7,
        "wind_speed": 4.7,
        "wind_gusts": 7.2
    },
    {
        "datetime": "2025-04-04T05:00",
        "daylight": "night",
        "lowtide": "",
        "wind_direction": 30,
        "wind_speed": 4.7,
        "wind_gusts": 7.6
    },
    {
        "datetime": "2025-04-04T06:00",
        "daylight": "night",
        "lowtide": "",
        "wind_direction": 28,
        "wind_speed": 4.2,
        "wind_gusts": 7.0
    },
    {
        "datetime": "2025-04-04T07:00",
        "daylight": "day",
        "lowtide": "",
        "wind_direction": 45,
        "wind_speed": 4.7,
        "wind_gusts": 7.8
    },
    {
        "datetime": "2025-04-04T08:00",
        "daylight": "day",
        "lowtide": "low",
        "wind_direction": 35,
        "wind_speed": 4.7,
        "wind_gusts": 7.6
    },
    {
        "datetime": "2025-04-04T09:00",
        "daylight": "day",
        "lowtide": "low",
        "wind_direction": 52,
        "wind_speed": 5.4,
        "wind_gusts": 8.4
    },
    {
        "datetime": "2025-04-04T10:00",
        "daylight": "day",
        "lowtide": "low",
        "wind_direction": 63,
        "wind_speed": 7.8,
        "wind_gusts": 12.6
    },
    {
        "datetime": "2025-04-04T11:00",
        "daylight": "day",
        "lowtide": "low",
        "wind_direction": 78,
        "wind_speed": 9.3,
        "wind_gusts": 15.2
    },
    {
        "datetime": "2025-04-04T12:00",
        "daylight": "day",
        "lowtide": "",
        "wind_direction": 88,
        "wind_speed": 10.5,
        "wind_gusts": 17.3
    },
    {
        "datetime": "2025-04-04T13:00",
        "daylight": "day",
        "lowtide": "",
        "wind_direction": 94,
        "wind_speed": 10.5,
        "wind_gusts": 17.9
    },
    {
        "datetime": "2025-04-04T14:00",
        "daylight": "day",
        "lowtide": "",
        "wind_direction": 108,
        "wind_speed": 9.8,
        "wind_gusts": 17.3
    },
    {
        "datetime": "2025-04-04T15:00",
        "daylight": "day",
        "lowtide": "",
        "wind_direction": 99,
        "wind_speed": 11.8,
        "wind_gusts": 19.0
    },
    {
        "datetime": "2025-04-04T16:00",
        "daylight": "day",
        "lowtide": "",
        "wind_direction": 95,
        "wind_speed": 12.5,
        "wind_gusts": 20.8
    },
    {
        "datetime": "2025-04-04T17:00",
        "daylight": "day",
        "lowtide": "",
        "wind_direction": 99,
        "wind_speed": 10.0,
        "wind_gusts": 20.0
    },
    {
        "datetime": "2025-04-04T18:00",
        "daylight": "day",
        "lowtide": "",
        "wind_direction": 89,
        "wind_speed": 8.0,
        "wind_gusts": 15.7
    },
    {
        "datetime": "2025-04-04T19:00",
        "daylight": "day",
        "lowtide": "",
        "wind_direction": 59,
        "wind_speed": 11.2,
        "wind_gusts": 19.2
    },
    {
        "datetime": "2025-04-04T20:00",
        "daylight": "night",
        "lowtide": "",
        "wind_direction": 50,
        "wind_speed": 11.2,
        "wind_gusts": 18.1
    },
    {
        "datetime": "2025-04-04T21:00",
        "daylight": "night",
        "lowtide": "low",
        "wind_direction": 49,
        "wind_speed": 12.1,
        "wind_gusts": 19.4
    },
    {
        "datetime": "2025-04-04T22:00",
        "daylight": "night",
        "lowtide": "low",
        "wind_direction": 47,
        "wind_speed": 13.3,
        "wind_gusts": 21.2
    },
    {
        "datetime": "2025-04-04T23:00",
        "daylight": "night",
        "lowtide": "low",
        "wind_direction": 46,
        "wind_speed": 13.9,
        "wind_gusts": 22.2
    },
    {
        "datetime": "2025-04-05T00:00",
        "daylight": "night",
        "lowtide": "",
        "wind_direction": 46,
        "wind_speed": 14.4,
        "wind_gusts": 22.9
    },
    {
        "datetime": "2025-04-05T01:00",
        "daylight": "night",
        "lowtide": "",
        "wind_direction": 46,
        "wind_speed": 14.6,
        "wind_gusts": 23.1
    },
    {
        "datetime": "2025-04-05T02:00",
        "daylight": "night",
        "lowtide": "",
        "wind_direction": 44,
        "wind_speed": 14.4,
        "wind_gusts": 23.3
    },
    {
        "datetime": "2025-04-05T03:00",
        "daylight": "night",
        "lowtide": "",
        "wind_direction": 44,
        "wind_speed": 14.6,
        "wind_gusts": 23.3
    },
    {
        "datetime": "2025-04-05T04:00",
        "daylight": "night",
        "lowtide": "",
        "wind_direction": 44,
        "wind_speed": 15.0,
        "wind_gusts": 24.1
    },
    {
        "datetime": "2025-04-05T05:00",
        "daylight": "night",
        "lowtide": "",
        "wind_direction": 43,
        "wind_speed": 14.9,
        "wind_gusts": 24.1
    },
    {
        "datetime": "2025-04-05T06:00",
        "daylight": "night",
        "lowtide": "",
        "wind_direction": 43,
        "wind_speed": 13.2,
        "wind_gusts": 23.5
    },
    {
        "datetime": "2025-04-05T07:00",
        "daylight": "day",
        "lowtide": "",
        "wind_direction": 40,
        "wind_speed": 13.9,
        "wind_gusts": 22.9
    },
    {
        "datetime": "2025-04-05T08:00",
        "daylight": "day",
        "lowtide": "",
        "wind_direction": 40,
        "wind_speed": 14.5,
        "wind_gusts": 23.1
    },
    {
        "datetime": "2025-04-05T09:00",
        "daylight": "day",
        "lowtide": "low",
        "wind_direction": 44,
        "wind_speed": 15.7,
        "wind_gusts": 25.3
    },
    {
        "datetime": "2025-04-05T10:00",
        "daylight": "day",
        "lowtide": "low",
        "wind_direction": 45,
        "wind_speed": 15.4,
        "wind_gusts": 25.3
    },
    {
        "datetime": "2025-04-05T11:00",
        "daylight": "day",
        "lowtide": "low",
        "wind_direction": 46,
        "wind_speed": 15.4,
        "wind_gusts": 25.3
    },
    {
        "datetime": "2025-04-05T12:00",
        "daylight": "day",
        "lowtide": "low",
        "wind_direction": 49,
        "wind_speed": 15.3,
        "wind_gusts": 24.9
    },
    {
        "datetime": "2025-04-05T13:00",
        "daylight": "day",
        "lowtide": "",
        "wind_direction": 53,
        "wind_speed": 16.3,
        "wind_gusts": 26.2
    },
    {
        "datetime": "2025-04-05T14:00",
        "daylight": "day",
        "lowtide": "",
        "wind_direction": 54,
        "wind_speed": 16.7,
        "wind_gusts": 27.2
    },
    {
        "datetime": "2025-04-05T15:00",
        "daylight": "day",
        "lowtide": "",
        "wind_direction": 56,
        "wind_speed": 16.4,
        "wind_gusts": 27.2
    },
    {
        "datetime": "2025-04-05T16:00",
        "daylight": "day",
        "lowtide": "",
        "wind_direction": 56,
        "wind_speed": 16.1,
        "wind_gusts": 26.6
    },
    {
        "datetime": "2025-04-05T17:00",
        "daylight": "day",
        "lowtide": "",
        "wind_direction": 55,
        "wind_speed": 16.1,
        "wind_gusts": 26.0
    },
    {
        "datetime": "2025-04-05T18:00",
        "daylight": "day",
        "lowtide": "",
        "wind_direction": 54,
        "wind_speed": 15.9,
        "wind_gusts": 25.7
    },
    {
        "datetime": "2025-04-05T19:00",
        "daylight": "day",
        "lowtide": "",
        "wind_direction": 53,
        "wind_speed": 15.8,
        "wind_gusts": 25.7
    },
    {
        "datetime": "2025-04-05T20:00",
        "daylight": "night",
        "lowtide": "",
        "wind_direction": 53,
        "wind_speed": 15.4,
        "wind_gusts": 25.3
    },
    {
        "datetime": "2025-04-05T21:00",
        "daylight": "night",
        "lowtide": "",
        "wind_direction": 52,
        "wind_speed": 15.2,
        "wind_gusts": 24.7
    },
    {
        "datetime": "2025-04-05T22:00",
        "daylight": "night",
        "lowtide": "low",
        "wind_direction": 50,
        "wind_speed": 15.2,
        "wind_gusts": 24.5
    },
    {
        "datetime": "2025-04-05T23:00",
        "daylight": "night",
        "lowtide": "low",
        "wind_direction": 49,
        "wind_speed": 15.2,
        "wind_gusts": 24.1
    },
    {
        "datetime": "2025-04-06T00:00",
        "daylight": "night",
        "lowtide": "",
        "wind_direction": 49,
        "wind_speed": 15.4,
        "wind_gusts": 24.7
    },
    {
        "datetime": "2025-04-06T01:00",
        "daylight": "night",
        "lowtide": "",
        "wind_direction": 48,
        "wind_speed": 14.6,
        "wind_gusts": 24.5
    },
    {
        "datetime": "2025-04-06T02:00",
        "daylight": "night",
        "lowtide": "",
        "wind_direction": 47,
        "wind_speed": 12.9,
        "wind_gusts": 22.5
    },
    {
        "datetime": "2025-04-06T03:00",
        "daylight": "night",
        "lowtide": "",
        "wind_direction": 48,
        "wind_speed": 12.0,
        "wind_gusts": 21.6
    },
    {
        "datetime": "2025-04-06T04:00",
        "daylight": "night",
        "lowtide": "",
        "wind_direction": 48,
        "wind_speed": 11.3,
        "wind_gusts": 19.8
    },
    {
        "datetime": "2025-04-06T05:00",
        "daylight": "night",
        "lowtide": "",
        "wind_direction": 46,
        "wind_speed": 11.0,
        "wind_gusts": 18.9
    },
    {
        "datetime": "2025-04-06T06:00",
        "daylight": "night",
        "lowtide": "",
        "wind_direction": 46,
        "wind_speed": 11.0,
        "wind_gusts": 18.5
    },
    {
        "datetime": "2025-04-06T07:00",
        "daylight": "day",
        "lowtide": "",
        "wind_direction": 44,
        "wind_speed": 10.9,
        "wind_gusts": 18.1
    },
    {
        "datetime": "2025-04-06T08:00",
        "daylight": "day",
        "lowtide": "",
        "wind_direction": 48,
        "wind_speed": 12.3,
        "wind_gusts": 20.4
    },
    {
        "datetime": "2025-04-06T09:00",
        "daylight": "day",
        "lowtide": "",
        "wind_direction": 53,
        "wind_speed": 12.6,
        "wind_gusts": 21.4
    },
    {
        "datetime": "2025-04-06T10:00",
        "daylight": "day",
        "lowtide": "",
        "wind_direction": 65,
        "wind_speed": 14.2,
        "wind_gusts": 23.9
    },
    {
        "datetime": "2025-04-06T11:00",
        "daylight": "day",
        "lowtide": "low",
        "wind_direction": 73,
        "wind_speed": 13.8,
        "wind_gusts": 23.9
    },
    {
        "datetime": "2025-04-06T12:00",
        "daylight": "day",
        "lowtide": "low",
        "wind_direction": 81,
        "wind_speed": 13.0,
        "wind_gusts": 23.3
    },
    {
        "datetime": "2025-04-06T13:00",
        "daylight": "day",
        "lowtide": "low",
        "wind_direction": 85,
        "wind_speed": 12.5,
        "wind_gusts": 21.8
    },
    {
        "datetime": "2025-04-06T14:00",
        "daylight": "day",
        "lowtide": "low",
        "wind_direction": 89,
        "wind_speed": 11.7,
        "wind_gusts": 21.0
    },
    {
        "datetime": "2025-04-06T15:00",
        "daylight": "day",
        "lowtide": "",
        "wind_direction": 90,
        "wind_speed": 11.1,
        "wind_gusts": 19.6
    },
    {
        "datetime": "2025-04-06T16:00",
        "daylight": "day",
        "lowtide": "",
        "wind_direction": 79,
        "wind_speed": 11.3,
        "wind_gusts": 19.0
    },
    {
        "datetime": "2025-04-06T17:00",
        "daylight": "day",
        "lowtide": "",
        "wind_direction": 67,
        "wind_speed": 12.6,
        "wind_gusts": 21.0
    },
    {
        "datetime": "2025-04-06T18:00",
        "daylight": "day",
        "lowtide": "",
        "wind_direction": 65,
        "wind_speed": 13.1,
        "wind_gusts": 22.0
    },
    {
        "datetime": "2025-04-06T19:00",
        "daylight": "day",
        "lowtide": "",
        "wind_direction": 62,
        "wind_speed": 12.3,
        "wind_gusts": 22.0
    },
    {
        "datetime": "2025-04-06T20:00",
        "daylight": "night",
        "lowtide": "",
        "wind_direction": 58,
        "wind_speed": 11.0,
        "wind_gusts": 20.4
    },
    {
        "datetime": "2025-04-06T21:00",
        "daylight": "night",
        "lowtide": "",
        "wind_direction": 52,
        "wind_speed": 11.1,
        "wind_gusts": 18.5
    },
    {
        "datetime": "2025-04-06T22:00",
        "daylight": "night",
        "lowtide": "",
        "wind_direction": 54,
        "wind_speed": 11.3,
        "wind_gusts": 18.9
    },
    {
        "datetime": "2025-04-06T23:00",
        "daylight": "night",
        "lowtide": "",
        "wind_direction": 53,
        "wind_speed": 10.4,
        "wind_gusts": 18.7
    },
    {
        "datetime": "2025-04-07T00:00",
        "daylight": "night",
        "lowtide": "low",
        "wind_direction": 52,
        "wind_speed": 9.7,
        "wind_gusts": 17.1
    },
    {
        "datetime": "2025-04-07T01:00",
        "daylight": "night",
        "lowtide": "low",
        "wind_direction": 50,
        "wind_speed": 8.4,
        "wind_gusts": 15.9
    },
    {
        "datetime": "2025-04-07T02:00",
        "daylight": "night",
        "lowtide": "low",
        "wind_direction": 47,
        "wind_speed": 8.0,
        "wind_gusts": 15.0
    },
    {
        "datetime": "2025-04-07T03:00",
        "daylight": "night",
        "lowtide": "",
        "wind_direction": 44,
        "wind_speed": 7.8,
        "wind_gusts": 14.0
    },
    {
        "datetime": "2025-04-07T04:00",
        "daylight": "night",
        "lowtide": "",
        "wind_direction": 41,
        "wind_speed": 7.7,
        "wind_gusts": 13.0
    },
    {
        "datetime": "2025-04-07T05:00",
        "daylight": "night",
        "lowtide": "",
        "wind_direction": 40,
        "wind_speed": 7.3,
        "wind_gusts": 12.6
    },
    {
        "datetime": "2025-04-07T06:00",
        "daylight": "night",
        "lowtide": "",
        "wind_direction": 38,
        "wind_speed": 6.9,
        "wind_gusts": 12.1
    },
    {
        "datetime": "2025-04-07T07:00",
        "daylight": "day",
        "lowtide": "",
        "wind_direction": 42,
        "wind_speed": 7.0,
        "wind_gusts": 11.7
    },
    {
        "datetime": "2025-04-07T08:00",
        "daylight": "day",
        "lowtide": "",
        "wind_direction": 49,
        "wind_speed": 8.0,
        "wind_gusts": 13.8
    },
    {
        "datetime": "2025-04-07T09:00",
        "daylight": "day",
        "lowtide": "",
        "wind_direction": 57,
        "wind_speed": 9.7,
        "wind_gusts": 15.7
    },
    {
        "datetime": "2025-04-07T10:00",
        "daylight": "day",
        "lowtide": "",
        "wind_direction": 64,
        "wind_speed": 10.6,
        "wind_gusts": 17.9
    },
    {
        "datetime": "2025-04-07T11:00",
        "daylight": "day",
        "lowtide": "",
        "wind_direction": 73,
        "wind_speed": 10.6,
        "wind_gusts": 17.7
    },
    {
        "datetime": "2025-04-07T12:00",
        "daylight": "day",
        "lowtide": "low",
        "wind_direction": 83,
        "wind_speed": 10.2,
        "wind_gusts": 17.3
    },
    {
        "datetime": "2025-04-07T13:00",
        "daylight": "day",
        "lowtide": "low",
        "wind_direction": 95,
        "wind_speed": 9.6,
        "wind_gusts": 17.1
    },
    {
        "datetime": "2025-04-07T14:00",
        "daylight": "day",
        "lowtide": "low",
        "wind_direction": 109,
        "wind_speed": 8.4,
        "wind_gusts": 16.3
    },
    {
        "datetime": "2025-04-07T15:00",
        "daylight": "day",
        "lowtide": "low",
        "wind_direction": 127,
        "wind_speed": 7.5,
        "wind_gusts": 15.7
    },
    {
        "datetime": "2025-04-07T16:00",
        "daylight": "day",
        "lowtide": "",
        "wind_direction": 142,
        "wind_speed": 6.9,
        "wind_gusts": 15.0
    },
    {
        "datetime": "2025-04-07T17:00",
        "daylight": "day",
        "lowtide": "",
        "wind_direction": 148,
        "wind_speed": 6.2,
        "wind_gusts": 12.6
    },
    {
        "datetime": "2025-04-07T18:00",
        "daylight": "day",
        "lowtide": "",
        "wind_direction": 148,
        "wind_speed": 4.8,
        "wind_gusts": 10.5
    },
    {
        "datetime": "2025-04-07T19:00",
        "daylight": "day",
        "lowtide": "",
        "wind_direction": 137,
        "wind_speed": 3.7,
        "wind_gusts": 8.2
    },
    {
        "datetime": "2025-04-07T20:00",
        "daylight": "night",
        "lowtide": "",
        "wind_direction": 102,
        "wind_speed": 3.8,
        "wind_gusts": 9.7
    },
    {
        "datetime": "2025-04-07T21:00",
        "daylight": "night",
        "lowtide": "",
        "wind_direction": 72,
        "wind_speed": 5.7,
        "wind_gusts": 11.1
    },
    {
        "datetime": "2025-04-07T22:00",
        "daylight": "night",
        "lowtide": "",
        "wind_direction": 62,
        "wind_speed": 7.5,
        "wind_gusts": 12.6
    },
    {
        "datetime": "2025-04-07T23:00",
        "daylight": "night",
        "lowtide": "",
        "wind_direction": 58,
        "wind_speed": 7.8,
        "wind_gusts": 12.2
    },
    {
        "datetime": "2025-04-08T00:00",
        "daylight": "night",
        "lowtide": "",
        "wind_direction": 56,
        "wind_speed": 7.3,
        "wind_gusts": 11.9
    },
    {
        "datetime": "2025-04-08T01:00",
        "daylight": "night",
        "lowtide": "low",
        "wind_direction": 53,
        "wind_speed": 6.5,
        "wind_gusts": 11.5
    },
    {
        "datetime": "2025-04-08T02:00",
        "daylight": "night",
        "lowtide": "low",
        "wind_direction": 49,
        "wind_speed": 5.9,
        "wind_gusts": 10.5
    },
    {
        "datetime": "2025-04-08T03:00",
        "daylight": "night",
        "lowtide": "low",
        "wind_direction": 42,
        "wind_speed": 5.5,
        "wind_gusts": 9.7
    },
    {
        "datetime": "2025-04-08T04:00",
        "daylight": "night",
        "lowtide": "low",
        "wind_direction": 39,
        "wind_speed": 5.3,
        "wind_gusts": 8.7
    },
    {
        "datetime": "2025-04-08T05:00",
        "daylight": "night",
        "lowtide": "",
        "wind_direction": 37,
        "wind_speed": 5.1,
        "wind_gusts": 8.9
    },
    {
        "datetime": "2025-04-08T06:00",
        "daylight": "night",
        "lowtide": "",
        "wind_direction": 39,
        "wind_speed": 5.3,
        "wind_gusts": 9.1
    },
    {
        "datetime": "2025-04-08T07:00",
        "daylight": "day",
        "lowtide": "",
        "wind_direction": 42,
        "wind_speed": 5.8,
        "wind_gusts": 9.3
    },
    {
        "datetime": "2025-04-08T08:00",
        "daylight": "day",
        "lowtide": "",
        "wind_direction": 45,
        "wind_speed": 6.9,
        "wind_gusts": 11.5
    },
    {
        "datetime": "2025-04-08T09:00",
        "daylight": "day",
        "lowtide": "",
        "wind_direction": 50,
        "wind_speed": 8.4,
        "wind_gusts": 13.8
    },
    {
        "datetime": "2025-04-08T10:00",
        "daylight": "day",
        "lowtide": "",
        "wind_direction": 54,
        "wind_speed": 9.2,
        "wind_gusts": 15.9
    },
    {
        "datetime": "2025-04-08T11:00",
        "daylight": "day",
        "lowtide": "",
        "wind_direction": 62,
        "wind_speed": 9.0,
        "wind_gusts": 15.4
    },
    {
        "datetime": "2025-04-08T12:00",
        "daylight": "day",
        "lowtide": "",
        "wind_direction": 73,
        "wind_speed": 8.5,
        "wind_gusts": 15.0
    },
    {
        "datetime": "2025-04-08T13:00",
        "daylight": "day",
        "lowtide": "low",
        "wind_direction": 86,
        "wind_speed": 7.8,
        "wind_gusts": 14.4
    },
    {
        "datetime": "2025-04-08T14:00",
        "daylight": "day",
        "lowtide": "low",
        "wind_direction": 103,
        "wind_speed": 6.8,
        "wind_gusts": 14.2
    },
    {
        "datetime": "2025-04-08T15:00",
        "daylight": "day",
        "lowtide": "low",
        "wind_direction": 128,
        "wind_speed": 6.4,
        "wind_gusts": 13.8
    },
    {
        "datetime": "2025-04-08T16:00",
        "daylight": "day",
        "lowtide": "low",
        "wind_direction": 143,
        "wind_speed": 6.5,
        "wind_gusts": 13.6
    },
    {
        "datetime": "2025-04-08T17:00",
        "daylight": "day",
        "lowtide": "",
        "wind_direction": 142,
        "wind_speed": 6.0,
        "wind_gusts": 11.7
    },
    {
        "datetime": "2025-04-08T18:00",
        "daylight": "day",
        "lowtide": "",
        "wind_direction": 130,
        "wind_speed": 4.8,
        "wind_gusts": 9.5
    },
    {
        "datetime": "2025-04-08T19:00",
        "daylight": "day",
        "lowtide": "",
        "wind_direction": 117,
        "wind_speed": 4.3,
        "wind_gusts": 7.6
    },
    {
        "datetime": "2025-04-08T20:00",
        "daylight": "night",
        "lowtide": "",
        "wind_direction": 65,
        "wind_speed": 9.8,
        "wind_gusts": 18.3
    },
    {
        "datetime": "2025-04-08T21:00",
        "daylight": "night",
        "lowtide": "",
        "wind_direction": 64,
        "wind_speed": 9.7,
        "wind_gusts": 18.3
    },
    {
        "datetime": "2025-04-08T22:00",
        "daylight": "night",
        "lowtide": "",
        "wind_direction": 62,
        "wind_speed": 9.2,
        "wind_gusts": 18.1
    },
    {
        "datetime": "2025-04-08T23:00",
        "daylight": "night",
        "lowtide": "",
        "wind_direction": 57,
        "wind_speed": 8.3,
        "wind_gusts": 16.3
    },
    {
        "datetime": "2025-04-09T00:00",
        "daylight": "night",
        "lowtide": "",
        "wind_direction": 51,
        "wind_speed": 7.0,
        "wind_gusts": 14.8
    },
    {
        "datetime": "2025-04-09T01:00",
        "daylight": "night",
        "lowtide": "",
        "wind_direction": 43,
        "wind_speed": 6.3,
        "wind_gusts": 13.0
    },
    {
        "datetime": "2025-04-09T02:00",
        "daylight": "night",
        "lowtide": "low",
        "wind_direction": 39,
        "wind_speed": 6.2,
        "wind_gusts": 12.8
    },
    {
        "datetime": "2025-04-09T03:00",
        "daylight": "night",
        "lowtide": "low",
        "wind_direction": 38,
        "wind_speed": 6.6,
        "wind_gusts": 12.8
    },
    {
        "datetime": "2025-04-09T04:00",
        "daylight": "night",
        "lowtide": "low",
        "wind_direction": 38,
        "wind_speed": 6.9,
        "wind_gusts": 12.6
    },
    {
        "datetime": "2025-04-09T05:00",
        "daylight": "night",
        "lowtide": "low",
        "wind_direction": 38,
        "wind_speed": 6.9,
        "wind_gusts": 13.0
    },
    {
        "datetime": "2025-04-09T06:00",
        "daylight": "night",
        "lowtide": "",
        "wind_direction": 38,
        "wind_speed": 7.2,
        "wind_gusts": 13.2
    },
    {
        "datetime": "2025-04-09T07:00",
        "daylight": "day",
        "lowtide": "",
        "wind_direction": 41,
        "wind_speed": 7.4,
        "wind_gusts": 13.6
    },
    {
        "datetime": "2025-04-09T08:00",
        "daylight": "day",
        "lowtide": "",
        "wind_direction": 43,
        "wind_speed": 8.3,
        "wind_gusts": 15.7
    },
    {
        "datetime": "2025-04-09T09:00",
        "daylight": "day",
        "lowtide": "",
        "wind_direction": 46,
        "wind_speed": 9.2,
        "wind_gusts": 17.7
    },
    {
        "datetime": "2025-04-09T10:00",
        "daylight": "day",
        "lowtide": "",
        "wind_direction": 50,
        "wind_speed": 10.1,
        "wind_gusts": 19.8
    },
    {
        "datetime": "2025-04-09T11:00",
        "daylight": "day",
        "lowtide": "",
        "wind_direction": 58,
        "wind_speed": 10.6,
        "wind_gusts": 20.8
    },
    {
        "datetime": "2025-04-09T12:00",
        "daylight": "day",
        "lowtide": "",
        "wind_direction": 66,
        "wind_speed": 11.1,
        "wind_gusts": 21.8
    },
    {
        "datetime": "2025-04-09T13:00",
        "daylight": "day",
        "lowtide": "",
        "wind_direction": 71,
        "wind_speed": 11.5,
        "wind_gusts": 22.7
    },
    {
        "datetime": "2025-04-09T14:00",
        "daylight": "day",
        "lowtide": "low",
        "wind_direction": 73,
        "wind_speed": 11.4,
        "wind_gusts": 22.2
    },
    {
        "datetime": "2025-04-09T15:00",
        "daylight": "day",
        "lowtide": "low",
        "wind_direction": 73,
        "wind_speed": 11.0,
        "wind_gusts": 21.6
    },
    {
        "datetime": "2025-04-09T16:00",
        "daylight": "day",
        "lowtide": "low",
        "wind_direction": 72,
        "wind_speed": 10.4,
        "wind_gusts": 21.0
    },
    {
        "datetime": "2025-04-09T17:00",
        "daylight": "day",
        "lowtide": "low",
        "wind_direction": 72,
        "wind_speed": 10.0,
        "wind_gusts": 20.4
    },
    {
        "datetime": "2025-04-09T18:00",
        "daylight": "day",
        "lowtide": "",
        "wind_direction": 72,
        "wind_speed": 9.6,
        "wind_gusts": 19.8
    },
    {
        "datetime": "2025-04-09T19:00",
        "daylight": "day",
        "lowtide": "",
        "wind_direction": 72,
        "wind_speed": 9.0,
        "wind_gusts": 19.2
    },
    {
        "datetime": "2025-04-09T20:00",
        "daylight": "night",
        "lowtide": "",
        "wind_direction": 72,
        "wind_speed": 8.0,
        "wind_gusts": 16.5
    },
    {
        "datetime": "2025-04-09T21:00",
        "daylight": "night",
        "lowtide": "",
        "wind_direction": 68,
        "wind_speed": 6.9,
        "wind_gusts": 13.6
    },
    {
        "datetime": "2025-04-09T22:00",
        "daylight": "night",
        "lowtide": "",
        "wind_direction": 65,
        "wind_speed": 6.0,
        "wind_gusts": 10.9
    },
    {
        "datetime": "2025-04-09T23:00",
        "daylight": "night",
        "lowtide": "",
        "wind_direction": 59,
        "wind_speed": 5.7,
        "wind_gusts": 10.9
    },
    {
        "datetime": "2025-04-10T00:00",
        "daylight": "night",
        "lowtide": "",
        "wind_direction": 54,
        "wind_speed": 5.6,
        "wind_gusts": 10.7
    },
    {
        "datetime": "2025-04-10T01:00",
        "daylight": "night",
        "lowtide": "",
        "wind_direction": 48,
        "wind_speed": 5.5,
        "wind_gusts": 10.7
    },
    {
        "datetime": "2025-04-10T02:00",
        "daylight": "night",
        "lowtide": "",
        "wind_direction": 43,
        "wind_speed": 5.1,
        "wind_gusts": 9.9
    },
    {
        "datetime": "2025-04-10T03:00",
        "daylight": "night",
        "lowtide": "low",
        "wind_direction": 40,
        "wind_speed": 4.8,
        "wind_gusts": 9.3
    },
    {
        "datetime": "2025-04-10T04:00",
        "daylight": "night",
        "lowtide": "low",
        "wind_direction": 38,
        "wind_speed": 4.4,
        "wind_gusts": 8.6
    },
    {
        "datetime": "2025-04-10T05:00",
        "daylight": "night",
        "lowtide": "low",
        "wind_direction": 34,
        "wind_speed": 4.2,
        "wind_gusts": 8.2
    },
    {
        "datetime": "2025-04-10T06:00",
        "daylight": "night",
        "lowtide": "low",
        "wind_direction": 33,
        "wind_speed": 3.9,
        "wind_gusts": 8.0
    },
    {
        "datetime": "2025-04-10T07:00",
        "daylight": "day",
        "lowtide": "",
        "wind_direction": 35,
        "wind_speed": 4.0,
        "wind_gusts": 7.6
    },
    {
        "datetime": "2025-04-10T08:00",
        "daylight": "day",
        "lowtide": "",
        "wind_direction": 45,
        "wind_speed": 4.9,
        "wind_gusts": 9.7
    },
    {
        "datetime": "2025-04-10T09:00",
        "daylight": "day",
        "lowtide": "",
        "wind_direction": 54,
        "wind_speed": 6.3,
        "wind_gusts": 11.7
    },
    {
        "datetime": "2025-04-10T10:00",
        "daylight": "day",
        "lowtide": "",
        "wind_direction": 58,
        "wind_speed": 7.1,
        "wind_gusts": 13.8
    },
    {
        "datetime": "2025-04-10T11:00",
        "daylight": "day",
        "lowtide": "",
        "wind_direction": 63,
        "wind_speed": 6.8,
        "wind_gusts": 13.4
    },
    {
        "datetime": "2025-04-10T12:00",
        "daylight": "day",
        "lowtide": "",
        "wind_direction": 69,
        "wind_speed": 5.8,
        "wind_gusts": 12.8
    },
    {
        "datetime": "2025-04-10T13:00",
        "daylight": "day",
        "lowtide": "",
        "wind_direction": 77,
        "wind_speed": 5.2,
        "wind_gusts": 12.4
    },
    {
        "datetime": "2025-04-10T14:00",
        "daylight": "day",
        "lowtide": "",
        "wind_direction": 85,
        "wind_speed": 4.9,
        "wind_gusts": 11.7
    },
    {
        "datetime": "2025-04-10T15:00",
        "daylight": "day",
        "lowtide": "low",
        "wind_direction": 97,
        "wind_speed": 4.7,
        "wind_gusts": 10.9
    },
    {
        "datetime": "2025-04-10T16:00",
        "daylight": "day",
        "lowtide": "low",
        "wind_direction": 107,
        "wind_speed": 4.7,
        "wind_gusts": 10.1
    },
    {
        "datetime": "2025-04-10T17:00",
        "daylight": "day",
        "lowtide": "low",
        "wind_direction": 123,
        "wind_speed": 4.6,
        "wind_gusts": 10.1
    },
    {
        "datetime": "2025-04-10T18:00",
        "daylight": "day",
        "lowtide": "low",
        "wind_direction": 137,
        "wind_speed": 4.8,
        "wind_gusts": 9.9
    },
    {
        "datetime": "2025-04-10T19:00",
        "daylight": "day",
        "lowtide": "",
        "wind_direction": 146,
        "wind_speed": 4.9,
        "wind_gusts": 9.9
    },
    {
        "datetime": "2025-04-10T20:00",
        "daylight": "night",
        "lowtide": "",
        "wind_direction": 146,
        "wind_speed": 4.2,
        "wind_gusts": 8.2
    },
    {
        "datetime": "2025-04-10T21:00",
        "daylight": "night",
        "lowtide": "",
        "wind_direction": 140,
        "wind_speed": 3.0,
        "wind_gusts": 6.6
    },
    {
        "datetime": "2025-04-10T22:00",
        "daylight": "night",
        "lowtide": "",
        "wind_direction": 131,
        "wind_speed": 2.1,
        "wind_gusts": 4.9
    },
    {
        "datetime": "2025-04-10T23:00",
        "daylight": "night",
        "lowtide": "",
        "wind_direction": 120,
        "wind_speed": 1.6,
        "wind_gusts": 4.1
    }
]